burst/__init__.py
burst/burst.py
burst/burst_cli.py
burst/lcloud.py
burst/runrun.py
burst/verbos.py
burst/version.py
burst/config/__init__.py
burst/config/config.py
burst/config/config_file_utils.py
burst/config/config_template.yml
burst/config/configurers.py
burst/config/cred_loaders.py
burst/config/menus.py
burst/config/summary.py
burstable-1.2.1.data/scripts/burst
burstable-1.2.1.data/scripts/burst-config
burstable-1.2.1.data/scripts/burst-monitor
burstable-1.2.1.dist-info/LICENSE
burstable-1.2.1.dist-info/METADATA
burstable-1.2.1.dist-info/WHEEL
burstable-1.2.1.dist-info/top_level.txt
burstable-1.2.1.dist-info/RECORD
