Metadata-Version: 2.1
Name: burstable
Version: 1.2.1
Summary: UNKNOWN
Home-page: UNKNOWN
License: UNKNOWN
Platform: UNKNOWN
Requires-Python: >=3.6
Requires-Dist: blessings (<2,>=1.7)
Requires-Dist: apache-libcloud (<4,>=3.2.0)
Requires-Dist: cryptography (<4,>=3.2)
Requires-Dist: easydict (<2,>=1.9)
Requires-Dist: PyYAML (<6,>=5.3.1)
